perm_montecarlo/__init__.py
perm_montecarlo/_perm_montecarlo.cp38-win_amd64.pyd
perm_montecarlo/plot/__init__.py
perm_montecarlo/plot/plot.py
perm_montecarlo-0.1.1.dist-info/METADATA
perm_montecarlo-0.1.1.dist-info/WHEEL
perm_montecarlo-0.1.1.dist-info/top_level.txt
perm_montecarlo-0.1.1.dist-info/RECORD
